func_analyzer/__init__.py
func_analyzer/analyzer.py
func_analyzer/utils.py
func_analyzer-0.1.1.dist-info/licenses/LICENSE
func_analyzer-0.1.1.dist-info/METADATA
func_analyzer-0.1.1.dist-info/WHEEL
func_analyzer-0.1.1.dist-info/top_level.txt
func_analyzer-0.1.1.dist-info/RECORD
