Metadata-Version: 2.4
Name: func-analyzer
Version: 0.1.1
Summary: A Python module for analyzing functions and extracting metadata including parameters, type hints, and docstrings
Author-email: Sisung Kim <sisung.kim1@gmail.com>
Requires-Python: >=3.10
License-File: LICENSE
Requires-Dist: docstring-parser>=0.15
Requires-Dist: pydantic>=2.0.0
Provides-Extra: dev
Requires-Dist: pytest>=7.0.0; extra == "dev"
Requires-Dist: pytest-cov>=4.0.0; extra == "dev"
Requires-Dist: black>=23.0.0; extra == "dev"
Requires-Dist: isort>=5.12.0; extra == "dev"
Requires-Dist: mypy>=1.0.0; extra == "dev"
Dynamic: license-file
